{"intheatres": [{"title": "Sanju", "thumbnail": "https://api.fyi.lk/public/movie/thumb/thumb_sanjuposter-1530165955.jpg", "genres": ["Biographical", "Drama"], "trailer": "https://www.youtube.com/watch?v=1J76wN0TPI4", "theatres": ["Liberty By Scope Cinemas - Liberty Screen 02", "Savoy Premier By EAP Movies -Wellawatte"]}, {"title": "Semma Botha Aagathey", "thumbnail": "https://api.fyi.lk/public/movie/thumb/thumb_Semma_Botha_Aagatha_thumb-1530267743.jpg", "genres": ["Action", "Thriller"], "trailer": "https://www.youtube.com/watch?v=KSD5Gn5s7wE", "theatres": ["Concord By EAP Movies -Dehiwala"]}, {"title": "Tik Tik Tik", "thumbnail": "https://api.fyi.lk/public/movie/thumb/thumb_tik_tik_thumb_img-1529909890.jpg", "genres": ["Action", "Adventure", "Sci-Fi"], "trailer": "https://www.youtube.com/watch?v=6ug9zvC9pJM", "theatres": ["Concord By EAP Movies -Dehiwala", "Samantha By EAP Movies -Dematagoda"]}, {"title": "Incredibles 2", "thumbnail": "https://api.fyi.lk/public/movie/thumb/thumb_Incredibles2poster-1528110142.jpg", "genres": ["Action", "Adventure", "Animation"], "trailer": "https://www.youtube.com/watch?v=i5qOzqD9Rms", "theatres": ["Liberty By Scope Cinemas - Liberty Screen 02", "Savoy 3D By EAP Movies -Wellawatte", "Savoy 2 By EAP Movies -Wellawatte", "Excel 3D By EAP Movies -Colombo 10"]}, {"title": "Jurassic World: Fallen Ki...", "thumbnail": "https://api.fyi.lk/public/movie/thumb/thumb_juraworldthumb-1528104701.jpg", "genres": ["Action", "Adventure", "Science fiction"], "trailer": "https://www.youtube.com/watch?v=vn9mMeWcgoM", "theatres": ["Liberty By Scope Cinemas - Liberty Screen 01", "Savoy 3D By EAP Movies -Wellawatte", "Savoy 2 By EAP Movies -Wellawatte", "Excel 3D By EAP Movies -Colombo 10", "Cinemax 3D By EAP Movies -Jaela", "Queens 3D By EAP Movies -Galle", "Sinexpo 3D By EAP Movies -Kurunegala", "Willmax 3D By EAP Movies -Anuradhapura", "Jothi 3D By EAP Movies -Rathnapura"]}, {"title": "Bimba Devi Hewath Yasodar...", "thumbnail": "https://api.fyi.lk/public/movie/thumb/thumb_yashodarathumb-1528109089.jpg", "genres": ["Biography", "Drama", "History"], "trailer": "https://www.youtube.com/watch?v=z64V06tBevs", "theatres": ["Cinemax 3D By EAP Movies -Jaela", "Samantha By EAP Movies -Dematagoda", "Savoy Premier By EAP Movies -Wellawatte", "Sinexpo 3D By EAP Movies -Kurunegala", "Willmax 3D By EAP Movies -Anuradhapura", "Queens 3D By EAP Movies -Galle", "Jothi 3D By EAP Movies -Rathnapura", "Regal By EAP Movies -Ambalangoda", "Tower By EAP Movies -Moratuwa", "C K Cinema By EAP Movies -Kirindiwela", "Prisca By EAP Movies -Kaluthara", "S.K By EAP Movies -Mathara", "Nikado By EAP Movies -Kadawatha", "Jayabima Cinema By EAP Movies -Gampola", "Lakbima By EAP Movies -Kuliyapitiya", "New Town By EAP Movies -Embilipitiya", "Cinesha By EAP Movies -Nawalapitiya", "Tarzan Cinema By EAP Movies -Kegall", "Vijayanthi By EAP Movies -Kaduwela", "Dharshana By EAP Movies -Koswadiya", "Cinelma By EAP Movies -Badulla", "Lekha By EAP Movies -Homagama", "Sigiri By EAP Movies -Katugasthota", "Regal Ampara By EAP Movies -Ampara"]}], "upcoming": [{"title": "Ant-Man and the Wasp", "thumbnail": "https://api.fyi.lk/public/movie/thumb/thumb_antthumb-1528246944.jpg", "genres": ["Action", "Adventure", "Sci-Fi"], "trailer": "https://www.youtube.com/watch?v=8_rTIAOohas"}, {"title": "Skyscraper", "thumbnail": "https://api.fyi.lk/public/movie/thumb/thumb_skycrapperthumb-1528117863.jpg", "genres": ["Action", "Crime", "Drama"], "trailer": "https://www.youtube.com/watch?v=t9QePUT-Yt8"}, {"title": "Hotel Transylvania 3: Sum...", "thumbnail": "https://api.fyi.lk/public/movie/thumb/thumb_movie6-1528119802.jpg", "genres": ["Animation", "Comedy", "Family"], "trailer": "https://www.youtube.com/watch?v=6jxGhgSEvHQ"}, {"title": "The Nun", "thumbnail": "https://api.fyi.lk/public/movie/thumb/thumb_the_nun_Thumb_Image-1529906739.jpg", "genres": ["Horror", "Mystery", "Thriller"], "trailer": "https://www.youtube.com/watch?v=4-ea_2jelYM"}, {"title": "Mamma Mia! Here We Go Aga...", "thumbnail": "https://api.fyi.lk/public/movie/thumb/thumb_maamathumb-1528244010.jpg", "genres": ["Comedy", "Music"], "trailer": "https://www.youtube.com/watch?v=XcSMdhfKga4"}, {"title": "Mission: Impossible - Fal...", "thumbnail": "https://api.fyi.lk/public/movie/thumb/thumb_movie5-1528118916.jpg", "genres": ["Action", "Adventure", "Thriller"], "trailer": "https://www.youtube.com/watch?v=wb49-oV0F78"}, {"title": "The Equalizer 2", "thumbnail": "https://api.fyi.lk/public/movie/thumb/thumb_Equalizer_thumb_image_-1529913128.jpg", "genres": ["Action", "Crime", "Thriller"], "trailer": "https://www.youtube.com/watch?v=HyNJ3UrGk_I"}, {"title": "The Darkest Minds", "thumbnail": "https://api.fyi.lk/public/movie/thumb/thumb_the_darkest_minds-1529998952.jpg", "genres": ["Sci-Fi", "Thriller"], "trailer": "https://www.youtube.com/watch?v=tN8o_E_f9FQ"}, {"title": "The Meg", "thumbnail": "https://api.fyi.lk/public/movie/thumb/thumb_meg_thumb_2-1529990654.jpg", "genres": ["Action", "Horror", "Sci-Fi"], "trailer": "https://www.youtube.com/watch?v=GGYXExfKhmo"}, {"title": "Slender Man", "thumbnail": "https://api.fyi.lk/public/movie/thumb/thumb_slendermanthumb-1528114893.jpg", "genres": ["Horror"], "trailer": "https://www.youtube.com/watch?v=ySy8mcceTno"}, {"title": "Venom", "thumbnail": "https://api.fyi.lk/public/movie/thumb/thumb_venom-1529350360.jpg", "genres": ["Action", "Horror", "Sci-Fi"], "trailer": "https://www.youtube.com/watch?v=u9Mv98Gr5pY"}]}